pydrive2/__init__.py
pydrive2/apiattr.py
pydrive2/auth.py
pydrive2/drive.py
pydrive2/files.py
pydrive2/settings.py
pydrive2/__pyinstaller/__init__.py
pydrive2/__pyinstaller/hook-googleapiclient.py
pydrive2/__pyinstaller/test_hook-googleapiclient.py
pydrive2/fs/__init__.py
pydrive2/fs/spec.py
pydrive2/fs/utils.py
pydrive2/test/__init__.py
pydrive2/test/test_apiattr.py
pydrive2/test/test_drive.py
pydrive2/test/test_file.py
pydrive2/test/test_filelist.py
pydrive2/test/test_fs.py
pydrive2/test/test_oauth.py
pydrive2/test/test_util.py
PyDrive2-1.21.3.dist-info/LICENSE
PyDrive2-1.21.3.dist-info/METADATA
PyDrive2-1.21.3.dist-info/WHEEL
PyDrive2-1.21.3.dist-info/entry_points.txt
PyDrive2-1.21.3.dist-info/top_level.txt
PyDrive2-1.21.3.dist-info/RECORD
