Metadata-Version: 2.1
Name: PyDrive2
Version: 1.21.3
Summary: Google Drive API made easy. Maintained fork of PyDrive.
Home-page: https://github.com/iterative/PyDrive2
Author: JunYoung Gwak
Author-email: jgwak@dreamylab.com
Maintainer: DVC team
Maintainer-email: support@dvc.org
License: Apache License 2.0
Project-URL: Documentation, https://docs.iterative.ai/PyDrive2
Project-URL: Changelog, https://github.com/iterative/PyDrive2/releases
Classifier: Development Status :: 4 - Beta
Classifier: Programming Language :: Python :: 3
Classifier: Programming Language :: Python :: 3.8
Classifier: Programming Language :: Python :: 3.9
Classifier: Programming Language :: Python :: 3.10
Classifier: Programming Language :: Python :: 3.11
Requires-Python: >=3.8
License-File: LICENSE
Requires-Dist: google-api-python-client>=1.12.5
Requires-Dist: oauth2client>=4.0.0
Requires-Dist: PyYAML>=3.0
Requires-Dist: cryptography<44
Requires-Dist: pyOpenSSL<=24.2.1,>=19.1.0
Provides-Extra: fsspec
Requires-Dist: fsspec>=2021.07.0; extra == "fsspec"
Requires-Dist: tqdm>=4.0.0; extra == "fsspec"
Requires-Dist: funcy>=1.14; extra == "fsspec"
Requires-Dist: appdirs>=1.4.3; extra == "fsspec"
Provides-Extra: tests
Requires-Dist: pytest>=4.6.0; extra == "tests"
Requires-Dist: timeout-decorator; extra == "tests"
Requires-Dist: funcy>=1.14; extra == "tests"
Requires-Dist: flake8; extra == "tests"
Requires-Dist: flake8-docstrings; extra == "tests"
Requires-Dist: pytest-mock; extra == "tests"
Requires-Dist: pyinstaller; extra == "tests"
Requires-Dist: importlib_resources<6; python_version < "3.10" and extra == "tests"
Requires-Dist: black==24.10.0; extra == "tests"
